TC2_8bit/src/cu.v
module CU (
        input clk,
        input rst_n,

        inout [7:0] bus,

        output reg PC_inc,

        output reg [3:0] ALU_Ctrl,
        output reg [3:0] JMP_Ctrl,
        output reg [3:0] MMU_Ctrl,

        output reg A_E,
        output reg A_L,
        output reg B_E,
        output reg B_L,
        output reg S_E,
        output reg SP_E
    );

    //0 - instruction load
    //1 - operand load
    //2 - execution
    reg [1:0] status;
    reg halt;
    reg waiting;
    reg write_waiting;
    reg operand;
    reg [7:0] operand_buffer;

    reg [7:0] instruction;

    reg bus_enable;
    reg [7:0] out;

    assign bus = (bus_enable) ? out : 8'bZ;

    always @(negedge clk) begin
        ALU_Ctrl = 4'd0;
        JMP_Ctrl = 4'd0;
        MMU_Ctrl = 4'd0;

        bus_enable = 0;

        A_E = 0;
        B_E = 0;
        S_E = 0;
        B_L = 0;
        A_L = 0;

        if (rst_n & !halt) begin
            case (status)
                0 : begin
                    if (!waiting) begin //opcode load
                        if (!write_waiting) begin
                            PC_inc <= 1;
                            MMU_Ctrl <= 4'b0110;
                            waiting <= 1;
                        end else write_waiting <= 0;
                    end else begin //store opcode in instruction register
                        PC_inc <= 0;
                        instruction <= bus;
                        waiting <= 0;
                        if (bus[5:4] != 2'b00) begin
                            status <= 2'd1;
                        end else status <= 2'd2;
                    end
                end
                1 : begin
                    if (!operand) begin //first operand
                        if (!waiting) begin //operand load
                            PC_inc <= 1;
                            MMU_Ctrl = 4'b0110;
                            waiting <= 1;
                        end else begin //store operand in MMU//JMP address low for memory reads, store result in operand buffer for immediate loads
                            PC_inc <= 0;
                            if (!instruction[4]) begin
                                if (instruction[7]) begin
                                    JMP_Ctrl <= 4'b0001;
                                end else begin
                                    MMU_Ctrl <= 4'b0001;
                                end
                                operand <= 1;
                            end else begin
                                operand_buffer <= bus;
                                waiting <= 0;
                                status <= 2'd2;
                            end
                            waiting <= 0;
                        end
                    end else begin //second operand
                        if (!waiting) begin //operand load
                            PC_inc <= 1;
                            MMU_Ctrl <= 4'b0110;
                            waiting <= 1;
                        end else begin //store operand in MMU//JMP address low for memory reads, store result in operand buffer for immediate loads
                            PC_inc <= 0;
                            if (instruction[7]) begin
                                JMP_Ctrl <= 4'b0010;
                            end else begin
                                MMU_Ctrl <= 4'b0010;
                            end
                            operand <= 0;
                            waiting <= 0;
                            status <= 2'd2;
                        end
                    end
                end
                2 : begin
                    PC_inc <= 0;
                    if (instruction == 8'd0) halt <= 1; //halt
                    case (instruction[7:6])
                        2'b00 : begin //ALU operation
                            case (instruction[5:4])
                                2'b00 :  //B register
                                    B_E <= 1;
                                2'b01 : begin //Indexed memory
                                    MMU_Ctrl <= 4'b0111;
                                end
                                2'b10 : begin //Memory
                                    MMU_Ctrl <= 4'b0101;
                                end
                                2'b11 : begin //Immediate operand
                                    out <= operand_buffer;
                                    bus_enable <= 1;
                                end
                            endcase
                            ALU_Ctrl <= instruction[3:0];
                        end
                        2'b01 : begin //register transfer
                            case (instruction[3:0])
                                4'b0001 : begin // A to target
                                    A_E <= 1;
                                    case (instruction[5:4])
                                        2'b00 :  //B register
                                            B_L <= 1;
                                        2'b01 : begin //Indexed memory
                                            write_waiting <= 1;
                                            MMU_Ctrl <= 4'b0101;
                                        end
                                        2'b10 : begin //Memory
                                            write_waiting <= 1;
                                            MMU_Ctrl <= 4'b0100;
                                        end
                                        2'b11 : halt <= 1; //Illegal (write to immediate)
                                    endcase
                                end
                                4'b0010 : begin // target to A
                                    A_L <= 1;
                                    case (instruction[5:4])
                                        2'b00 :  //B register
                                            B_E <= 1;
                                        2'b01 : begin //Indexed memory
                                            MMU_Ctrl <= 4'b0111;
                                        end
                                        2'b10 : begin //Memory
                                            MMU_Ctrl <= 4'b0101;
                                        end
                                        2'b11 : begin //Immediate operand
                                            out <= operand_buffer;
                                            bus_enable <= 1;
                                        end
                                    endcase
                                end
                                4'b0011 : begin // B to target
                                    B_E <= 1;
                                    case (instruction[5:4])
                                        2'b00 :  //Illegal (B to B)
                                            halt <= 1;
                                        2'b01 : begin //Indexed memory
                                            write_waiting <= 1;
                                            MMU_Ctrl <= 4'b0101;
                                        end
                                        2'b10 : begin //Memory
                                            write_waiting <= 1;
                                            MMU_Ctrl <= 4'b0100;
                                        end
                                        2'b11 : halt <= 1; //Illegal (write to immediate)
                                    endcase
                                end
                                4'b0100 : begin // target to B
                                    B_L <= 1;
                                    case (instruction[5:4])
                                        2'b00 :  //Illegal (B to B)
                                            halt <= 1;
                                        2'b01 : begin //Indexed memory
                                            MMU_Ctrl <= 4'b0111;
                                        end
                                        2'b10 : begin //Memory
                                            MMU_Ctrl <= 4'b0101;
                                        end
                                        2'b11 : begin //Immediate operand
                                            out <= operand_buffer;
                                            bus_enable <= 1;
                                        end
                                    endcase
                                end
                                4'b0101 : begin //Misc. register transfer
                                    case (instruction[5:4])
                                        2'b00 : begin //Sum to A
                                            S_E <= 1;
                                            A_L <= 1;
                                        end
                                        2'b01 : begin //Sum to B
                                            S_E <= 1;
                                            B_L <= 1;
                                        end
                                        2'b10 : begin //SP to A
                                            SP_E <= 1;
                                            A_L <= 1;
                                        end
                                        2'b11 : begin //SP to B
                                            SP_E <= 1;
                                            B_L <= 1;
                                        end
                                    endcase
                                end
                            endcase
                        end
                        2'b10 : begin //jump
                            JMP_Ctrl <= instruction[3:0];
                            write_waiting <= 1;
                        end
                        2'b11 : begin //stack
                            case (instruction[3:0]) 
                                4'b0001 : begin //Push
                                    case (instruction[5:4])
                                        2'b00 : begin //B register
                                            B_E <= 1;
                                            MMU_Ctrl <= 4'b1001;
                                            write_waiting <= 1;
                                        end
                                        2'b01 : begin //A register
                                            A_E <= 1;
                                            MMU_Ctrl <= 4'b1001;
                                            write_waiting <= 1;
                                        end
                                    endcase
                                end
                                4'b0010 : begin //Pop
                                    case (instruction[5:4])
                                        2'b00 : begin //B register
                                            B_L <= 1;
                                            MMU_Ctrl <= 4'b1011;
                                        end
                                        2'b01 : begin //A register
                                            A_L <= 1;
                                            MMU_Ctrl <= 4'b1011;
                                        end
                                        2'b10 : begin //Empty target
                                            MMU_Ctrl <= 4'b1011;
                                        end
                                    endcase
                                end
                            endcase
                        end
                    endcase
                    status <= 2'd0;
                end
            endcase
        end
    end

    always @(posedge rst_n) begin
        status <= 2'd0;
        halt <= 0;
        waiting <= 0;
        write_waiting <= 0;
        operand <= 0;
        operand_buffer <= 8'd0;

        instruction <= 8'd0;

        PC_inc <= 1;

        ALU_Ctrl <= 4'd0;
        JMP_Ctrl <= 4'd0;
        MMU_Ctrl <= 4'd0;

        A_E <= 0;
        A_L <= 0;
        B_E <= 0;
        B_L <= 0;
        S_E <= 0;
        SP_E <= 0;

        bus_enable <= 0;
        out <= 8'd0;
    end

endmodule

TC2_8bit/src/mmu.v
module MMU (
        input clk,
        input rst_n,

        inout [7:0] bus,

        input [3:0] MMU_Ctrl,

        input [7:0] B_Dir,

        inout [7:0] data_out,
        output [15:0] addr_out,
        output rW,

        input [15:0] PC,
        input [7:0] SP_Dir,
        output reg [1:0] SP_action
    );

    reg bus_enable;

    reg read;
    reg write;
    reg indexed;
    reg stack;

    reg write_L;

    reg [7:0] data_external;
    reg [15:0] addr_external;

    reg [15:0] address;

    assign bus = (bus_enable) ? data_out : 8'bZ;

    assign data_out = (write) ? data_external : 8'bZ;
    assign addr_out = (read || write) ? addr_external : 16'bZ;
    assign rW = read ? 1'b1 : (write ? 1'b0 : 1'bZ);

    always @(posedge clk) begin
        SP_action <= 2'd0;
        if (rst_n) begin
            if (MMU_Ctrl != 4'b0000) begin
                case (MMU_Ctrl)
                    4'b0001 : address[7:0] <= bus; //load low byte of addr
                    4'b0010 : address[15:8] <= bus; //load high byte of addr
                    4'b0011 : begin //Standard read
                        addr_external <= address; 
                        read <= 1;
                        bus_enable <= 1;
                    end
                    4'b0111 : begin //Standard indexed read
                        addr_external <= (address + B_Dir);
                        read <= 1;
                        bus_enable <= 1;
                    end
                    4'b0100 : begin //Latch write
                        bus_enable <= 0;
                        read <= 0;
                        write_L <= 1;
                    end
                    4'b0101 : begin //Latch indexed write
                        bus_enable <= 0;
                        read <= 0;
                        indexed <= 1;
                        write_L <= 1;
                    end
                    4'b0110 : begin //Opcode read
                        addr_external <= PC;
                        read <= 1;
                        bus_enable <= 1;
                    end
                    4'b1001 : begin //Latch stack push
                        bus_enable <= 0;
                        read <= 0;
                        stack <= 1;
                        write_L <= 1;
                    end
                    4'b1011 : begin //Stack pop
                        addr_external <= {8'b00000001, (SP_Dir + 8'd1)};
                        read <= 1;
                        bus_enable <= 1;
                        SP_action <= 2'b10;
                    end
                    default : begin
                        bus_enable <= 0;
                        read <= 0;
                        write_L <= 0;
                    end
                endcase
            end else begin
                bus_enable <= 0;
                read <= 0;
                write_L <= 0;
                stack <= 0;
                indexed <= 0;
            end
        end else bus_enable <= 0;
    end

    always @(negedge clk) begin
        if (rst_n) begin
            if (write_L) begin //load system bus into memory at address buffer
                if (indexed) begin
                    address = (address + B_Dir);
                end else if (stack) begin
                    address = {8'b00000001, SP_Dir};
                    SP_action = 2'b01;
                end
                addr_external <= address;
                data_external <= bus;
                bus_enable <= 0;
                write <= 1;
            end else begin
                write <= 0;
            end
        end else bus_enable <= 0;
    end

    always @(posedge rst_n) begin
        bus_enable <= 0;
        read <= 0;
        write <= 0;
        indexed <= 0;
        stack <= 0;

        SP_action <= 2'b00;

        data_external <= 16'd0;
        addr_external <= 16'd0;

        address <= 16'd0;
    end

endmodule

TC2_8bit/src/alu.v
module ALU (
        input clk,
        input rst_n,

        inout [7:0] bus,

        input [3:0] ALU_Ctrl,

        input [7:0] A_Dir,
        output [7:0] S_Dir_ALU,
        output reg S_L_ALU
    );

    reg [7:0] sum;
    reg [7:0] out;

    reg [3:0] ALU_Ctrl_L;
    reg [7:0] bus_L;

    assign S_Dir_ALU = (S_L_ALU) ? sum : 8'bZ;

    always @(posedge clk) begin
        if (ALU_Ctrl != 4'b0000) begin 
            ALU_Ctrl_L <= ALU_Ctrl;
            bus_L <= bus;
        end else begin
            ALU_Ctrl_L <= 0;
            bus_L <= 0;
        end
    end

    always @(negedge clk) begin
        if (rst_n) begin
            if (ALU_Ctrl_L != 4'b0000) begin
                case (ALU_Ctrl_L)
                    4'b0001 : sum = (A_Dir + bus_L); //self explanatory arithmetic
                    4'b0010 : sum = (A_Dir - bus_L);
                    4'b0011 : sum = (A_Dir & bus_L);
                    4'b0100 : sum = (A_Dir | bus_L);
                    4'b0101 : sum = (A_Dir ^ bus_L); 

                    4'b0110 : sum = (A_Dir << bus_L);
                    4'b0111 : sum = (A_Dir >> bus_L);

                    4'b1000 : sum = (A_Dir == bus_L);
                    4'b1001 : sum = (A_Dir != bus_L);
                    4'b1010 : sum = (A_Dir >  bus_L);
                    4'b1011 : sum = (A_Dir <  bus_L);
                    4'b1100 : sum = (A_Dir >= bus_L);
                    4'b1101 : sum = (A_Dir <= bus_L);
                endcase
                S_L_ALU = 1; 
            end else S_L_ALU = 0;
        end else S_L_ALU = 0;
    end;

    always @(posedge rst_n) begin
        sum <= 8'd0;
        out <= 8'd0;
        S_L_ALU <= 0;

        ALU_Ctrl_L <= 4'd0;
        bus_L <= 8'd0;
    end 


endmodule

module PCmover (
        input clk,
        input rst_n,

        input [7:0] bus,
        inout [15:0] PC_Dir,
        input [3:0] JMP_Ctrl,
        input [7:0] S_Dir_JMP,

        output reg PC_Dir_L
    );

    reg [15:0] PC_upd;

    reg [15:0] address;

    reg [3:0] JMP_Ctrl_L;

    assign PC_Dir = (PC_Dir_L) ? PC_upd : 16'bZ;

    always @(posedge clk) begin
        if (rst_n) begin
            if (JMP_Ctrl != 4'b0000) begin
                case (JMP_Ctrl)
                    4'b0001 : address[7:0] <= bus; //load low byte of addr
                    4'b0010 : address[15:8] <= bus; //load high byte of addr
                endcase
            end
            JMP_Ctrl_L <= JMP_Ctrl;
        end
    end

    always @(negedge clk) begin
        if (rst_n) begin
            if (JMP_Ctrl_L != 4'b0000) begin
                case (JMP_Ctrl_L)
                    4'b0011 : PC_upd <= address; //jump unconditionally
                    4'b0100 : begin //jump if S != 0
                        if (S_Dir_JMP != 7'd0) begin
                            PC_upd = address;
                            PC_Dir_L = 1;
                        end
                    end
                endcase
                PC_Dir_L = 1;
            end else PC_Dir_L = 0;
        end else PC_Dir_L = 0;
    end

    always @(posedge rst_n) begin
        PC_Dir_L <= 0;
        PC_upd <= 16'd0;

        JMP_Ctrl_L <= 4'd0;

        address <= 16'd0;
    end

endmodule

TC2_8bit/src/registers.v
module registers (
        input clk,
        input rst_n, 

        inout [7:0] bus,

        input A_E,
        input B_E,
        input S_E,
        input A_L,
        input B_L,
        input S_L_ALU,
        input PC_Dir_L,
        input SP_L,
        input SP_E,

        input PC_inc,
        input [1:0] SP_action,

        output [7:0] A_Dir,
        output [7:0] B_Dir,
        input [7:0] S_Dir_ALU,
        output [7:0] S_Dir_JMP,
        input [15:0] PC_Dir,
        output [15:0] PC_Dir_out,
        output [7:0] SP_Dir
    );

    reg [7:0] A;
    reg [7:0] B;
    reg [7:0] S;

    reg [15:0] PC;
    reg [7:0] SP;

    reg A_L_ready;
    reg B_L_ready;
    reg S_L_ready;
    reg PC_Dir_L_ready;

    assign bus = (A_E) ? A : 
                 (B_E) ? B :
                 (S_E) ? S : 
                 (SP_E) ? SP : 8'bZ;

    assign A_Dir = A;
    assign S_Dir_JMP = S;

    assign PC_Dir_out = PC;
    assign SP_Dir = SP;

    always @(negedge clk) begin
        if (rst_n) begin
            A <= (A_L_ready) ? bus : A;
            B <= (B_L_ready) ? bus : B;
            S <= (S_L_ready) ? S_Dir_ALU : S;
            PC <= (PC_Dir_L_ready) ? PC_Dir : PC;
        end
    end

    always @(posedge clk) begin
        if (rst_n) begin
            A_L_ready <= A_L;
            B_L_ready <= B_L;
            S_L_ready <= S_L_ALU;
            PC_Dir_L_ready <= PC_Dir_L;
            if (PC_inc)
                PC <= PC + 1;
            if (SP_action == 2'b01) begin
                SP <= SP - 1;
            end else if (SP_action == 2'b10) begin
                SP <= SP + 1;
            end
        end else begin
            PC <= 16'd0;
        end
    end

    always @(posedge rst_n) begin
        A <= 8'b0;
        B <= 8'b0;
        S <= 8'b0;
        PC <= 16'b0;
        SP <= 8'hFF;

        A_L_ready <= 0;
        B_L_ready <= 0;
        S_L_ready <= 0;
        PC_Dir_L_ready <= 0;
    end
endmodule

TC2_8bit/src/testbench.v
`timescale 1ns / 1ps

module testbench;
    reg clk;
    reg rst_n;
    wire [7:0] bus;
    wire [7:0] A_Dir;
    wire [7:0] B_Dir;
    wire [7:0] S_Dir_ALU;
    wire [7:0] S_Dir_JMP;
    wire [15:0] PC_Dir;
    wire [15:0] PC;
    wire [7:0] SP_Dir;
    wire [1:0] SP_action;
    wire PC_inc;

    wire [3:0] ALU_Ctrl;
    wire [3:0] JMP_Ctrl;
    wire [3:0] MMU_Ctrl;

    wire [7:0] data_ext;
    wire [15:0] addr_ext;
    wire rW;

    wire A_E;
    wire B_E;
    wire A_L;
    wire B_L;
    wire S_E;
    wire SP_E;
    wire S_L_ALU;
    
    wire PC_Dir_L;

    reg [7:0] rom [0:511];

    ALU ALU (
        .clk(clk),
        .rst_n(rst_n),
        .bus(bus),
        .A_Dir(A_Dir),
        .S_Dir_ALU(S_Dir_ALU),
        .S_L_ALU(S_L_ALU),
        .ALU_Ctrl(ALU_Ctrl)
    );

    registers registers (
        .clk(clk),
        .rst_n(rst_n),
        .bus(bus),
        .A_E(A_E),
        .B_E(B_E),
        .A_L(A_L),
        .B_L(B_L),
        .S_E(S_E),
        .SP_E(SP_E),
        .S_L_ALU(S_L_ALU),
        .PC_inc(PC_inc),
        .A_Dir(A_Dir),
        .B_Dir(B_Dir),
        .S_Dir_ALU(S_Dir_ALU),
        .S_Dir_JMP(S_Dir_JMP),
        .PC_Dir(PC_Dir),
        .PC_Dir_L(PC_Dir_L),
        .PC_Dir_out(PC),
        .SP_Dir(SP_Dir),
        .SP_action(SP_action)
    );

    PCmover PCmover (
        .clk(clk),
        .rst_n(rst_n),
        .bus(bus),
        .PC_Dir(PC_Dir),
        .PC_Dir_L(PC_Dir_L),
        .JMP_Ctrl(JMP_Ctrl),
        .S_Dir_JMP(S_Dir_JMP)
    );

    MMU MMU (
        .clk(clk),
        .rst_n(rst_n),
        .bus(bus),
        .B_Dir(B_Dir),
        .MMU_Ctrl(MMU_Ctrl),
        .data_out(data_ext),
        .addr_out(addr_ext),
        .rW(rW),
        .PC(PC),
        .SP_Dir(SP_Dir),
        .SP_action(SP_action)
    );

    CU CU (
        .clk(clk),
        .rst_n(rst_n),
        .bus(bus),
        .PC_inc(PC_inc),
        .ALU_Ctrl(ALU_Ctrl),
        .JMP_Ctrl(JMP_Ctrl),
        .MMU_Ctrl(MMU_Ctrl),
        .A_E(A_E),
        .A_L(A_L),
        .B_E(B_E),
        .B_L(B_L),
        .S_E(S_E),
        .SP_E(SP_E)
    );

    assign data_ext = (rW) ? rom[addr_ext] : 8'bZ;

    always begin
        #10 clk = ~clk; 
        if (!rW) rom[addr_ext] <= data_ext;
    end

    initial begin
        $readmemh("test_rom.txt", rom);

        clk = 0;
        rst_n = 0;
        
        $dumpfile("testbench_waveform.vcd");
        $dumpvars(0, testbench);

        #30 rst_n = 1;
        #1000;

        $display("Result at $01FF: %d", rom[16'h01FF]);

        $finish;
    end

endmodule

TC2_8bit/src/testbench_waveform.vcd
$date
	Mon Sep 28 20:59:51 2026
$end
$version
	Icarus Verilog
$end
$timescale
	1ps
$end
$scope module testbench $end
$var wire 8 ! B_Dir [7:0] $end
$var wire 8 " bus [7:0] $end
$var wire 8 # data_ext [7:0] $end
$var wire 1 $ rW $end
$var wire 16 % addr_ext [15:0] $end
$var wire 1 & S_L_ALU $end
$var wire 1 ' S_E $end
$var wire 8 ( S_Dir_JMP [7:0] $end
$var wire 8 ) S_Dir_ALU [7:0] $end
$var wire 2 * SP_action [1:0] $end
$var wire 1 + SP_E $end
$var wire 8 , SP_Dir [7:0] $end
$var wire 1 - PC_inc $end
$var wire 1 . PC_Dir_L $end
$var wire 16 / PC_Dir [15:0] $end
$var wire 16 0 PC [15:0] $end
$var wire 4 1 MMU_Ctrl [3:0] $end
$var wire 4 2 JMP_Ctrl [3:0] $end
$var wire 1 3 B_L $end
$var wire 1 4 B_E $end
$var wire 1 5 A_L $end
$var wire 1 6 A_E $end
$var wire 8 7 A_Dir [7:0] $end
$var wire 4 8 ALU_Ctrl [3:0] $end
$var reg 1 9 clk $end
$var reg 1 : rst_n $end
$scope module ALU $end
$var wire 8 ; bus [7:0] $end
$var wire 1 9 clk $end
$var wire 1 : rst_n $end
$var wire 8 < S_Dir_ALU [7:0] $end
$var wire 8 = A_Dir [7:0] $end
$var wire 4 > ALU_Ctrl [3:0] $end
$var reg 4 ? ALU_Ctrl_L [3:0] $end
$var reg 1 & S_L_ALU $end
$var reg 8 @ bus_L [7:0] $end
$var reg 8 A out [7:0] $end
$var reg 8 B sum [7:0] $end
$upscope $end
$scope module CU $end
$var wire 8 C bus [7:0] $end
$var wire 1 9 clk $end
$var wire 1 : rst_n $end
$var reg 4 D ALU_Ctrl [3:0] $end
$var reg 1 6 A_E $end
$var reg 1 5 A_L $end
$var reg 1 4 B_E $end
$var reg 1 3 B_L $end
$var reg 4 E JMP_Ctrl [3:0] $end
$var reg 4 F MMU_Ctrl [3:0] $end
$var reg 1 - PC_inc $end
$var reg 1 + SP_E $end
$var reg 1 ' S_E $end
$var reg 1 G bus_enable $end
$var reg 1 H halt $end
$var reg 8 I instruction [7:0] $end
$var reg 1 J operand $end
$var reg 8 K operand_buffer [7:0] $end
$var reg 8 L out [7:0] $end
$var reg 2 M status [1:0] $end
$var reg 1 N waiting $end
$var reg 1 O write_waiting $end
$upscope $end
$scope module MMU $end
$var wire 8 P B_Dir [7:0] $end
$var wire 4 Q MMU_Ctrl [3:0] $end
$var wire 8 R bus [7:0] $end
$var wire 1 9 clk $end
$var wire 8 S data_out [7:0] $end
$var wire 1 : rst_n $end
$var wire 1 $ rW $end
$var wire 16 T addr_out [15:0] $end
$var wire 8 U SP_Dir [7:0] $end
$var wire 16 V PC [15:0] $end
$var reg 2 W SP_action [1:0] $end
$var reg 16 X addr_external [15:0] $end
$var reg 16 Y address [15:0] $end
$var reg 1 Z bus_enable $end
$var reg 8 [ data_external [7:0] $end
$var reg 1 \ indexed $end
$var reg 1 ] read $end
$var reg 1 ^ stack $end
$var reg 1 _ write $end
$var reg 1 ` write_L $end
$upscope $end
$scope module PCmover $end
$var wire 4 a JMP_Ctrl [3:0] $end
$var wire 8 b bus [7:0] $end
$var wire 1 9 clk $end
$var wire 1 : rst_n $end
$var wire 8 c S_Dir_JMP [7:0] $end
$var wire 16 d PC_Dir [15:0] $end
$var reg 4 e JMP_Ctrl_L [3:0] $end
$var reg 1 . PC_Dir_L $end
$var reg 16 f PC_upd [15:0] $end
$var reg 16 g address [15:0] $end
$upscope $end
$scope module registers $end
$var wire 8 h A_Dir [7:0] $end
$var wire 1 6 A_E $end
$var wire 1 5 A_L $end
$var wire 8 i B_Dir [7:0] $end
$var wire 1 4 B_E $end
$var wire 1 3 B_L $end
$var wire 16 j PC_Dir [15:0] $end
$var wire 1 . PC_Dir_L $end
$var wire 16 k PC_Dir_out [15:0] $end
$var wire 1 - PC_inc $end
$var wire 8 l SP_Dir [7:0] $end
$var wire 1 + SP_E $end
$var wire 1 m SP_L $end
$var wire 2 n SP_action [1:0] $end
$var wire 8 o S_Dir_ALU [7:0] $end
$var wire 8 p S_Dir_JMP [7:0] $end
$var wire 1 ' S_E $end
$var wire 1 & S_L_ALU $end
$var wire 8 q bus [7:0] $end
$var wire 1 9 clk $end
$var wire 1 : rst_n $end
$var reg 8 r A [7:0] $end
$var reg 1 s A_L_ready $end
$var reg 8 t B [7:0] $end
$var reg 1 u B_L_ready $end
$var reg 16 v PC [15:0] $end
$var reg 1 w PC_Dir_L_ready $end
$var reg 8 x S [7:0] $end
$var reg 8 y SP [7:0] $end
$var reg 1 z S_L_ready $end
$upscope $end
$upscope $end
$enddefinitions $end
$comment Show the parameter values. $end
$dumpall
$end
#0
$dumpvars
xz
bx y
bx x
xw
bx v
xu
bx t
xs
bx r
bx q
bx p
bz o
bx n
zm
bx l
bx k
bz j
bz i
bx h
bx g
bx f
bx e
bz d
bx c
bx b
b0 a
x`
x_
x^
x]
x\
bx [
0Z
bx Y
bx X
bx W
bx V
bx U
bx T
bx S
bx R
b0 Q
bz P
xO
xN
bx M
bx L
bx K
xJ
bx I
xH
0G
b0 F
b0 E
b0 D
bx C
bx B
bx A
bx @
bx ?
b0 >
bx =
bz <
bx ;
0:
09
b0 8
bx 7
06
05
04
03
b0 2
b0 1
bx 0
bz /
0.
x-
bx ,
x+
bx *
bz )
bx (
0'
0&
bx %
x$
bx #
bx "
bz !
$end
#10000
b0 @
b0 ?
b0 0
b0 V
b0 k
b0 v
b0 *
b0 W
b0 n
19
#20000
09
#30000
bz "
bz ;
bz C
bz R
bz b
bz q
z$
bz %
bz T
0`
b0 A
b0 B
0w
0z
0u
0s
b11111111 ,
b11111111 U
b11111111 l
b11111111 y
b0 (
b0 c
b0 p
b0 x
b0 t
b0 7
b0 =
b0 h
b0 r
b0 g
b0 e
b0 f
b0 Y
b0 X
b0 [
0^
0\
0_
0]
b0 L
0+
1-
b0 I
b0 K
0J
0O
0N
0H
b0 M
19
1:
#40000
1N
b110 1
b110 F
b110 Q
09
#50000
b1110010 #
b1110010 S
b0 %
b0 T
b1110010 "
b1110010 ;
b1110010 C
b1110010 R
b1110010 b
b1110010 q
1$
b1 0
b1 V
b1 k
b1 v
1Z
1]
19
#60000
b1 M
0N
b1110010 I
0-
b0 1
b0 F
b0 Q
09
#70000
bx #
bx S
bz %
bz T
z$
bz "
bz ;
bz C
bz R
bz b
bz q
0]
0Z
19
#80000
1N
1-
b110 1
b110 F
b110 Q
09
#90000
b11000000 #
b11000000 S
b1 %
b1 T
b11000000 "
b11000000 ;
b11000000 C
b11000000 R
b11000000 b
b11000000 q
1$
b10 0
b10 V
b10 k
b10 v
1Z
1]
b1 X
19
#100000
b10 M
0N
b11000000 K
0-
b0 1
b0 F
b0 Q
09
#110000
bx #
bx S
bz %
bz T
z$
bz "
bz ;
bz C
bz R
bz b
bz q
0]
0Z
19
#120000
b11000000 "
b11000000 ;
b11000000 C
b11000000 R
b11000000 b
b11000000 q
b0 M
1G
b11000000 L
15
09
#130000
1s
19
#140000
1N
b110 1
b110 F
b110 Q
1-
b11000000 7
b11000000 =
b11000000 h
b11000000 r
bz "
bz ;
bz C
bz R
bz b
bz q
05
0G
09
#150000
b110001 #
b110001 S
b10 %
b10 T
b110001 "
b110001 ;
b110001 C
b110001 R
b110001 b
b110001 q
1$
1Z
1]
b10 X
b11 0
b11 V
b11 k
b11 v
0s
19
#160000
b1 M
0N
b110001 I
0-
b0 1
b0 F
b0 Q
09
#170000
bx #
bx S
bz %
bz T
z$
bz "
bz ;
bz C
bz R
bz b
bz q
0]
0Z
19
#180000
1N
1-
b110 1
b110 F
b110 Q
09
#190000
b1100 #
b1100 S
b11 %
b11 T
b1100 "
b1100 ;
b1100 C
b1100 R
b1100 b
b1100 q
1$
1Z
1]
b11 X
b100 0
b100 V
b100 k
b100 v
19
#200000
b10 M
0N
b1100 K
0-
b0 1
b0 F
b0 Q
09
#210000
bx #
bx S
bz %
bz T
z$
bz "
bz ;
bz C
bz R
bz b
bz q
0]
0Z
19
#220000
b1100 "
b1100 ;
b1100 C
b1100 R
b1100 b
b1100 q
b0 M
b1 8
b1 >
b1 D
1G
b1100 L
09
#230000
b1100 @
b1 ?
19
#240000
1N
b110 1
b110 F
b110 Q
1-
b11001100 )
b11001100 <
b11001100 o
bz "
bz ;
bz C
bz R
bz b
bz q
1&
b11001100 B
0G
b0 8
b0 >
b0 D
09
#250000
b1000101 #
b1000101 S
b100 %
b100 T
b1000101 "
b1000101 ;
b1000101 C
b1000101 R
b1000101 b
b1000101 q
1$
b0 @
b0 ?
b101 0
b101 V
b101 k
b101 v
1z
1Z
1]
b100 X
19
#260000
b10 M
0N
b1000101 I
0-
b11001100 (
b11001100 c
b11001100 p
b11001100 x
bz )
bz <
bz o
b0 1
b0 F
b0 Q
0&
09
#270000
bx #
bx S
bz %
bz T
z$
bz "
bz ;
bz C
bz R
bz b
bz q
0]
0Z
0z
19
#280000
b11001100 "
b11001100 ;
b11001100 C
b11001100 R
b11001100 b
b11001100 q
b0 M
15
1'
09
#290000
1s
19
#300000
1N
b110 1
b110 F
b110 Q
1-
b11001100 7
b11001100 =
b11001100 h
b11001100 r
bz "
bz ;
bz C
bz R
bz b
bz q
05
0'
09
#310000
b1110100 #
b1110100 S
b101 %
b101 T
b1110100 "
b1110100 ;
b1110100 C
b1110100 R
b1110100 b
b1110100 q
1$
1Z
1]
b101 X
b110 0
b110 V
b110 k
b110 v
0s
19
#320000
b1 M
0N
b1110100 I
0-
b0 1
b0 F
b0 Q
09
#330000
bx #
bx S
bz %
bz T
z$
bz "
bz ;
bz C
bz R
bz b
bz q
0]
0Z
19
#340000
1N
1-
b110 1
b110 F
b110 Q
09
#350000
b11001100 #
b11001100 S
b110 %
b110 T
b11001100 "
b11001100 ;
b11001100 C
b11001100 R
b11001100 b
b11001100 q
1$
1Z
1]
b110 X
b111 0
b111 V
b111 k
b111 v
19
#360000
b10 M
0N
b11001100 K
0-
b0 1
b0 F
b0 Q
09
#370000
bx #
bx S
bz %
bz T
z$
bz "
bz ;
bz C
bz R
bz b
bz q
0]
0Z
19
#380000
b11001100 "
b11001100 ;
b11001100 C
b11001100 R
b11001100 b
b11001100 q
b0 M
1G
b11001100 L
13
09
#390000
1u
19
#400000
b11001100 t
1N
b110 1
b110 F
b110 Q
1-
bz "
bz ;
bz C
bz R
bz b
bz q
03
0G
09
#410000
b1000 #
b1000 S
b111 %
b111 T
b1000 "
b1000 ;
b1000 C
b1000 R
b1000 b
b1000 q
1$
b1000 0
b1000 V
b1000 k
b1000 v
0u
1Z
1]
b111 X
19
#420000
b10 M
0N
b1000 I
0-
b0 1
b0 F
b0 Q
09
#430000
bx #
bx S
bz %
bz T
z$
bz "
bz ;
bz C
bz R
bz b
bz q
0]
0Z
19
#440000
b11001100 "
b11001100 ;
b11001100 C
b11001100 R
b11001100 b
b11001100 q
b0 M
b1000 8
b1000 >
b1000 D
14
09
#450000
b11001100 @
b1000 ?
19
#460000
1N
b110 1
b110 F
b110 Q
1-
bz "
bz ;
bz C
bz R
bz b
bz q
b1 )
b1 <
b1 o
04
b0 8
b0 >
b0 D
1&
b1 B
09
#470000
b10100100 #
b10100100 S
b1000 %
b1000 T
b10100100 "
b10100100 ;
b10100100 C
b10100100 R
b10100100 b
b10100100 q
1$
1Z
1]
b1000 X
b1001 0
b1001 V
b1001 k
b1001 v
1z
b0 @
b0 ?
19
#480000
b1 (
b1 c
b1 p
b1 x
b1 M
0N
b10100100 I
0-
bz )
bz <
bz o
0&
b0 1
b0 F
b0 Q
09
#490000
bx #
bx S
bz %
bz T
z$
bz "
bz ;
bz C
bz R
bz b
bz q
0z
0]
0Z
19
#500000
1N
1-
b110 1
b110 F
b110 Q
09
#510000
b10000 #
b10000 S
b1001 %
b1001 T
b10000 "
b10000 ;
b10000 C
b10000 R
b10000 b
b10000 q
1$
1Z
1]
b1001 X
b1010 0
b1010 V
b1010 k
b1010 v
19
#520000
0N
1J
b1 2
b1 E
b1 a
0-
b0 1
b0 F
b0 Q
09
#530000
bx #
bx S
bz %
bz T
z$
bz "
bz ;
bz C
bz R
bz b
bz q
b1 e
b10000 g
0]
0Z
19
