TC2_8bit/src/cu.v
module CU (
        input clk,
        input rst_n,

        inout [7:0] bus,

        output reg PC_inc,

        output reg [3:0] ALU_Ctrl,
        output reg [3:0] JMP_Ctrl,
        output reg [3:0] MMU_Ctrl,

        output reg A_E,
        output reg A_L,
        output reg B_E,
        output reg B_L,
        output reg S_E,
        output reg SP_E
    );

    //0 - instruction load
    //1 - operand load
    //2 - execution
    reg [1:0] status;
    reg halt;
    reg waiting;
    reg write_waiting;
    reg operand;
    reg [7:0] operand_buffer;

    reg [7:0] instruction;

    reg bus_enable;
    reg [7:0] out;

    assign bus = (bus_enable) ? out : 8'bZ;

    always @(negedge clk) begin
        ALU_Ctrl = 4'd0;
        JMP_Ctrl = 4'd0;
        MMU_Ctrl = 4'd0;

        bus_enable = 0;

        A_E = 0;
        B_E = 0;
        S_E = 0;
        B_L = 0;
        A_L = 0;

        if (rst_n & !halt) begin
            case (status)
                0 : begin
                    if (!waiting) begin //opcode load
                        if (!write_waiting) begin
                            PC_inc <= 1;
                            MMU_Ctrl <= 4'b0110;
                            waiting <= 1;
                        end else write_waiting <= 0;
                    end else begin //store opcode in instruction register
                        PC_inc <= 0;
                        instruction <= bus;
                        waiting <= 0;
                        if (bus[5]) begin
                            status <= 2'd1;
                        end else status <= 2'd2;
                    end
                end
                1 : begin
                    if (!operand) begin //first operand
                        if (!waiting) begin //operand load
                            PC_inc <= 1;
                            MMU_Ctrl = 4'b0110;
                            waiting <= 1;
                        end else begin //store operand in MMU//JMP address low for memory reads, store result in operand buffer for immediate loads
                            PC_inc <= 0;
                            if (!instruction[4]) begin
                                if (instruction[7]) begin
                                    JMP_Ctrl <= 4'b0001;
                                end else begin
                                    MMU_Ctrl <= 4'b0001;
                                end
                                operand <= 1;
                            end else begin
                                operand_buffer <= bus;
                                waiting <= 0;
                                status <= 2'd2;
                            end
                            waiting <= 0;
                        end
                    end else begin //second operand
                        if (!waiting) begin //operand load
                            PC_inc <= 1;
                            MMU_Ctrl <= 4'b0110;
                            waiting <= 1;
                        end else begin //store operand in MMU//JMP address low for memory reads, store result in operand buffer for immediate loads
                            PC_inc <= 0;
                            if (instruction[7]) begin
                                JMP_Ctrl <= 4'b0010;
                            end else begin
                                MMU_Ctrl <= 4'b0010;
                            end
                            operand <= 0;
                            waiting <= 0;
                            status <= 2'd2;
                        end
                    end
                end
                2 : begin
                    PC_inc <= 0;
                    if (instruction == 8'd0) halt <= 1; //halt
                    case (instruction[7:6])
                        2'b00 : begin //ALU operation
                            if (instruction[5]) begin //memory address
                                MMU_Ctrl <= 4'b0011;
                            end else begin
                                if (!instruction[4]) begin //b register
                                    B_E <= 1;
                                end else begin //sum register
                                    S_E <= 1;
                                end
                            end
                            ALU_Ctrl <= instruction[3:0];
                        end
                        2'b01 : begin //register transfer
                            case (instruction[3:0])
                                4'b0001 : begin // A to target
                                    A_E <= 1;
                                    case (instruction[5:4])
                                        2'b00 :  //B register
                                            B_L <= 1;
                                        2'b01 : begin //Indexed memory
                                            write_waiting <= 1;
                                            MMU_Ctrl <= 4'b0101;
                                        end
                                        2'b10 : begin //Memory
                                            write_waiting <= 1;
                                            MMU_Ctrl <= 4'b0100;
                                        end
                                        2'b11 : halt <= 1; //Illegal (write to immediate)
                                    endcase
                                end
                                4'b0010 : begin // target to A
                                    A_L <= 1;
                                    case (instruction[5:4])
                                        2'b00 :  //B register
                                            B_E <= 1;
                                        2'b01 : begin //Indexed memory
                                            MMU_Ctrl <= 4'b0111;
                                        end
                                        2'b10 : begin //Memory
                                            MMU_Ctrl <= 4'b0101;
                                        end
                                        2'b11 : begin //Immediate operand
                                            out <= operand_buffer;
                                            bus_enable <= 1;
                                        end
                                    endcase
                                end
                                4'b0011 : begin // B to target
                                    B_E <= 1;
                                    case (instruction[5:4])
                                        2'b00 :  //Illegal (B to B)
                                            halt <= 1;
                                        2'b01 : begin //Indexed memory
                                            write_waiting <= 1;
                                            MMU_Ctrl <= 4'b0101;
                                        end
                                        2'b10 : begin //Memory
                                            write_waiting <= 1;
                                            MMU_Ctrl <= 4'b0100;
                                        end
                                        2'b11 : halt <= 1; //Illegal (write to immediate)
                                    endcase
                                end
                                4'b0100 : begin // target to B
                                    B_L <= 1;
                                    case (instruction[5:4])
                                        2'b00 :  //Illegal (B to B)
                                            halt <= 1;
                                        2'b01 : begin //Indexed memory
                                            MMU_Ctrl <= 4'b0111;
                                        end
                                        2'b10 : begin //Memory
                                            MMU_Ctrl <= 4'b0101;
                                        end
                                        2'b11 : begin //Immediate operand
                                            out <= operand_buffer;
                                            bus_enable <= 1;
                                        end
                                    endcase
                                end
                                4'b0101 : begin //Misc. register transfer
                                    case (instruction[5:4])
                                        2'b00 : begin //Sum to A
                                            S_E <= 1;
                                            A_L <= 1;
                                        end
                                        2'b01 : begin //Sum to B
                                            S_E <= 1;
                                            B_L <= 1;
                                        end
                                        2'b10 : begin //SP to A
                                            SP_E <= 1;
                                            A_L <= 1;
                                        end
                                        2'b11 : begin //SP to B
                                            SP_E <= 1;
                                            B_L <= 1;
                                        end
                                    endcase
                                end
                            endcase
                        end
                        2'b10 : begin //jump
                            JMP_Ctrl <= instruction[3:0];
                        end
                        2'b11 : begin //stack
                            case (instruction[3:0]) 
                                4'b0001 : begin //Push
                                    case (instruction[5:4])
                                        2'b00 : begin //B register
                                            B_E <= 1;
                                            MMU_Ctrl <= 4'b1001;
                                            write_waiting <= 1;
                                        end
                                        2'b01 : begin //A register
                                            A_E <= 1;
                                            MMU_Ctrl <= 4'b1001;
                                            write_waiting <= 1;
                                        end
                                    endcase
                                end
                                4'b0010 : begin //Pop
                                    case (instruction[5:4])
                                        2'b00 : begin //B register
                                            B_L <= 1;
                                            MMU_Ctrl <= 4'b1011;
                                        end
                                        2'b01 : begin //A register
                                            A_L <= 1;
                                            MMU_Ctrl <= 4'b1011;
                                        end
                                        2'b10 : begin //Empty target
                                            MMU_Ctrl <= 4'b1011;
                                        end
                                    endcase
                                end
                            endcase
                        end
                    endcase
                    status <= 2'd0;
                end
            endcase
        end
    end

    always @(posedge rst_n) begin
        status <= 2'd0;
        halt <= 0;
        waiting <= 0;
        write_waiting <= 0;
        operand <= 0;
        operand_buffer <= 8'd0;

        instruction <= 8'd0;

        PC_inc <= 1;

        ALU_Ctrl <= 4'd0;
        JMP_Ctrl <= 4'd0;
        MMU_Ctrl <= 4'd0;

        A_E <= 0;
        A_L <= 0;
        B_E <= 0;
        B_L <= 0;
        S_E <= 0;
        SP_E <= 0;

        bus_enable <= 0;
        out <= 8'd0;
    end

endmodule

TC2_8bit/src/mmu.v
module MMU (
        input clk,
        input rst_n,

        inout [7:0] bus,

        input [3:0] MMU_Ctrl,

        input [7:0] B_Dir,

        inout [7:0] data_out,
        output [15:0] addr_out,
        output rW,

        input [15:0] PC,
        input [7:0] SP_Dir,
        output reg [1:0] SP_action
    );

    reg bus_enable;

    reg read;
    reg write;
    reg indexed;
    reg stack;

    reg write_L;

    reg [7:0] data_external;
    reg [15:0] addr_external;

    reg [15:0] address;

    assign bus = (bus_enable) ? data_out : 8'bZ;

    assign data_out = (write) ? data_external : 8'bZ;
    assign addr_out = (read || write) ? addr_external : 16'bZ;
    assign rW = read ? 1'b1 : (write ? 1'b0 : 1'bZ);

    always @(posedge clk) begin
        if (rst_n) begin
            if (MMU_Ctrl != 4'b0000) begin
                case (MMU_Ctrl)
                    4'b0001 : address[7:0] <= bus; //load low byte of addr
                    4'b0010 : address[15:8] <= bus; //load high byte of addr
                    4'b0011 : begin //Standard read
                        addr_external <= address; 
                        read <= 1;
                        bus_enable <= 1;
                    end
                    4'b0111 : begin //Standard indexed read
                        addr_external <= (address + B_Dir);
                        read <= 1;
                        bus_enable <= 1;
                    end
                    4'b0100 : begin //Latch write
                        bus_enable <= 0;
                        read <= 0;
                        write_L <= 1;
                    end
                    4'b0101 : begin //Latch indexed write
                        bus_enable <= 0;
                        read <= 0;
                        indexed <= 1;
                        write_L <= 1;
                    end
                    4'b0110 : begin //Opcode read
                        addr_external <= PC;
                        read <= 1;
                        bus_enable <= 1;
                    end
                    4'b1001 : begin //Latch stack push
                        bus_enable <= 0;
                        read <= 0;
                        stack <= 1;
                        write_L <= 1;
                    end
                    4'b1011 : begin //Stack pop
                        addr_external <= SP_Dir; 
                        read <= 1;
                        bus_enable <= 1;
                        SP_action <= 2'b10;
                    end
                    default : begin
                        bus_enable <= 0;
                        read <= 0;
                        write_L <= 0;
                    end
                endcase
            end else begin
                bus_enable <= 0;
                read <= 0;
                write_L <= 0;
                stack <= 0;
                indexed <= 0;
            end
        end else bus_enable <= 0;
    end

    always @(negedge clk) begin
        if (rst_n) begin
            if (write_L) begin //load system bus into memory at address buffer
                if (indexed) begin
                    address = (address + B_Dir);
                end else if (stack) begin
                    address = {8'b00000001, SP_Dir};
                    SP_action = 2'b01;
                end
                addr_external <= address;
                data_external <= bus;
                bus_enable <= 0;
                write <= 1;
            end else begin
                write <= 0;
            end
        end else bus_enable <= 0;
    end

    always @(posedge rst_n) begin
        bus_enable <= 0;
        read <= 0;
        write <= 0;
        indexed <= 0;
        stack <= 0;

        SP_action <= 2'b00;

        data_external <= 16'd0;
        addr_external <= 16'd0;

        address <= 16'd0;
    end

endmodule

TC2_8bit/src/alu.v
module ALU (
        input clk,
        input rst_n,

        inout [7:0] bus,

        input [3:0] ALU_Ctrl,

        input [7:0] A_Dir,
        output [7:0] S_Dir_ALU,
        output reg S_L_ALU
    );

    reg [7:0] sum;
    reg [7:0] out;

    assign S_Dir_ALU = (S_L_ALU) ? sum : 8'bZ;

    always @(negedge clk) begin
        if (rst_n) begin
            if (ALU_Ctrl != 4'b0000) begin
                case (ALU_Ctrl)
                    4'b0001 : sum = (A_Dir + bus); //self explanatory arithmetic
                    4'b0010 : sum = (A_Dir - bus);
                    4'b0011 : sum = (A_Dir & bus);
                    4'b0100 : sum = (A_Dir | bus);
                    4'b0101 : sum = (A_Dir ^ bus); 

                    4'b0110 : sum = (A_Dir << bus);
                    4'b0111 : sum = (A_Dir >> bus);

                    4'b1000 : sum = (A_Dir == bus);
                    4'b1001 : sum = (A_Dir != bus);
                    4'b1010 : sum = (A_Dir >  bus);
                    4'b1011 : sum = (A_Dir <  bus);
                    4'b1100 : sum = (A_Dir >= bus);
                    4'b1101 : sum = (A_Dir <= bus);
                endcase
                S_L_ALU = 1; 
            end else S_L_ALU = 0;
        end else S_L_ALU = 0;
    end;

    always @(posedge rst_n) begin
        sum <= 8'd0;
        out <= 8'd0;
        S_L_ALU <= 0;
    end 


endmodule

module PCmover (
        input clk,
        input rst_n,

        input [7:0] bus,
        inout [15:0] PC_Dir,
        input [3:0] JMP_Ctrl,
        input [7:0] S_Dir_JMP,

        output PC_Dir_L
    );

    reg active;
    reg [15:0] PC_upd;

    reg [15:0] address;

    assign PC_Dir_L = active;

    assign PC_Dir = (active) ? PC_upd : 16'bZ;

    always @(negedge clk) begin
        if (rst_n) begin
            if (JMP_Ctrl != 4'b0000) begin
                case (JMP_Ctrl)
                    4'b0001 : address[7:0] <= bus; //load low byte of addr
                    4'b0010 : address[15:8] <= bus; //load high byte of addr
                    4'b0011 : PC_upd = address; //jump unconditionally
                    4'b0100 : begin //jump if B != 0
                        if (S_Dir_JMP != 7'd0) begin
                            PC_upd = address;
                            active = 1;
                        end
                    end
                endcase
                active = 1;
            end else active = 0;
        end else active = 0;
    end

    always @(posedge rst_n) begin
        active <= 0;
        PC_upd <= 16'd0;
    end

endmodule

TC2_8bit/src/registers.v
module registers (
        input clk,
        input rst_n, 

        inout [7:0] bus,

        input A_E,
        input B_E,
        input S_E,
        input A_L,
        input B_L,
        input S_L_ALU,
        input PC_Dir_L,
        input SP_L,
        input SP_E,

        input PC_inc,
        input [1:0] SP_action,

        output [7:0] A_Dir,
        output [7:0] B_Dir,
        input [7:0] S_Dir_ALU,
        output [7:0] S_Dir_JMP,
        input [15:0] PC_Dir,
        output [15:0] PC_Dir_out,
        output [7:0] SP_Dir
    );

    reg [7:0] A;
    reg [7:0] B;
    reg [7:0] S;

    reg [15:0] PC;
    reg [7:0] SP;

    reg A_L_ready;
    reg B_L_ready;
    reg S_L_ready;

    assign bus = (A_E) ? A : 
                 (B_E) ? B :
                 (S_E) ? S : 
                 (SP_E) ? SP : 8'bZ;

    assign A_Dir = A;
    assign B_Dir_JMP = B;

    assign PC_Dir_out = PC;
    assign SP_Dir = SP;

    always @(negedge clk) begin
        if (rst_n) begin
            A <= (A_L_ready) ? bus : A;
            B <= (B_L_ready) ? bus : B;
            S <= (S_L_ready) ? S_Dir_ALU : S;
            PC <= (PC_Dir_L) ? PC_Dir : PC;
        end
    end

    always @(posedge clk) begin
        if (rst_n) begin
            A_L_ready <= A_L;
            B_L_ready <= B_L;
            S_L_ready <= S_L_ALU;
            if (PC_inc)
                PC <= PC + 1;
            if (SP_action == 2'b01) begin
                SP <= SP - 1;
            end else if (SP_action == 2'b10) begin
                SP <= SP + 1;
            end
        end else begin
            PC <= 16'd0;
        end
    end

    always @(posedge rst_n) begin
        A <= 8'b0;
        B <= 8'b0;
        S <= 8'b0;
        PC <= 16'b0;
        SP <= 8'hFF;

        A_L_ready <= 0;
        B_L_ready <= 0;
        S_L_ready <= 0;
    end
endmodule

TC2_8bit/src/testbench.v
`timescale 1ns / 1ps

module testbench;
    reg clk;
    reg rst_n;
    wire [7:0] bus;
    wire [7:0] A_Dir;
    wire [7:0] B_Dir;
    wire [7:0] S_Dir_ALU;
    wire [7:0] S_Dir_JMP;
    wire [15:0] PC_Dir;
    wire [15:0] PC;
    wire [7:0] SP_Dir;
    wire [1:0] SP_action;
    wire PC_inc;

    wire [3:0] ALU_Ctrl;
    wire [3:0] JMP_Ctrl;
    wire [3:0] MMU_Ctrl;

    wire [7:0] data_ext;
    wire [15:0] addr_ext;
    wire rW;

    wire A_E;
    wire B_E;
    wire A_L;
    wire B_L;
    wire S_E;
    wire SP_E;
    wire S_L_ALU;
    
    wire PC_Dir_L;

    reg [7:0] rom [0:511];

    ALU ALU (
        .clk(clk),
        .rst_n(rst_n),
        .bus(bus),
        .A_Dir(A_Dir),
        .S_Dir_ALU(S_Dir_ALU),
        .S_L_ALU(S_L_ALU),
        .ALU_Ctrl(ALU_Ctrl)
    );

    registers registers (
        .clk(clk),
        .rst_n(rst_n),
        .bus(bus),
        .A_E(A_E),
        .B_E(B_E),
        .A_L(A_L),
        .B_L(B_L),
        .S_E(S_E),
        .SP_E(SP_E),
        .S_L_ALU(S_L_ALU),
        .PC_inc(PC_inc),
        .A_Dir(A_Dir),
        .B_Dir(B_Dir),
        .S_Dir_ALU(S_Dir_ALU),
        .S_Dir_JMP(S_Dir_JMP),
        .PC_Dir(PC_Dir),
        .PC_Dir_L(PC_Dir_L),
        .PC_Dir_out(PC),
        .SP_Dir(SP_Dir)
    );

    PCmover PCmover (
        .clk(clk),
        .rst_n(rst_n),
        .bus(bus),
        .PC_Dir(PC_Dir),
        .PC_Dir_L(PC_Dir_L),
        .JMP_Ctrl(JMP_Ctrl),
        .S_Dir_JMP(S_Dir_JMP)
    );

    MMU MMU (
        .clk(clk),
        .rst_n(rst_n),
        .bus(bus),
        .B_Dir(B_Dir),
        .MMU_Ctrl(MMU_Ctrl),
        .data_out(data_ext),
        .addr_out(addr_ext),
        .rW(rW),
        .PC(PC),
        .SP_Dir(SP_Dir),
        .SP_action(SP_action)
    );

    CU CU (
        .clk(clk),
        .rst_n(rst_n),
        .bus(bus),
        .PC_inc(PC_inc),
        .ALU_Ctrl(ALU_Ctrl),
        .JMP_Ctrl(JMP_Ctrl),
        .MMU_Ctrl(MMU_Ctrl),
        .A_E(A_E),
        .A_L(A_L),
        .B_E(B_E),
        .B_L(B_L),
        .S_E(S_E),
        .SP_E(SP_E)
    );

    assign data_ext = (rW) ? rom[addr_ext] : 8'bZ;

    always begin
        #10 clk = ~clk; 
        if (!rW) rom[addr_ext] <= data_ext;
    end

    initial begin
        $readmemh("test_rom.txt", rom);

        clk = 0;
        rst_n = 0;
        
        $dumpfile("testbench_waveform.vcd");
        $dumpvars(0, testbench);

        #30 rst_n = 1;
        #1000;

        $display("Result at $01FF: %d", rom[16'h01FF]);

        $finish;
    end

endmodule

TC2_8bit/src/testbench_waveform.vcd
$date
	Sat Sep 26 19:39:43 2026
$end
$version
	Icarus Verilog
$end
$timescale
	1ps
$end
$scope module testbench $end
$var wire 8 ! B_Dir [7:0] $end
$var wire 8 " S_Dir_JMP [7:0] $end
$var wire 8 # bus [7:0] $end
$var wire 8 $ data_ext [7:0] $end
$var wire 1 % rW $end
$var wire 16 & addr_ext [15:0] $end
$var wire 1 ' S_L_ALU $end
$var wire 1 ( S_E $end
$var wire 8 ) S_Dir_ALU [7:0] $end
$var wire 2 * SP_action [1:0] $end
$var wire 1 + SP_E $end
$var wire 8 , SP_Dir [7:0] $end
$var wire 1 - PC_inc $end
$var wire 1 . PC_Dir_L $end
$var wire 16 / PC_Dir [15:0] $end
$var wire 16 0 PC [15:0] $end
$var wire 4 1 MMU_Ctrl [3:0] $end
$var wire 4 2 JMP_Ctrl [3:0] $end
$var wire 1 3 B_L $end
$var wire 1 4 B_E $end
$var wire 1 5 A_L $end
$var wire 1 6 A_E $end
$var wire 8 7 A_Dir [7:0] $end
$var wire 4 8 ALU_Ctrl [3:0] $end
$var reg 1 9 clk $end
$var reg 1 : rst_n $end
$scope module ALU $end
$var wire 8 ; bus [7:0] $end
$var wire 1 9 clk $end
$var wire 1 : rst_n $end
$var wire 8 < S_Dir_ALU [7:0] $end
$var wire 8 = A_Dir [7:0] $end
$var wire 4 > ALU_Ctrl [3:0] $end
$var reg 1 ' S_L_ALU $end
$var reg 8 ? out [7:0] $end
$var reg 8 @ sum [7:0] $end
$upscope $end
$scope module CU $end
$var wire 8 A bus [7:0] $end
$var wire 1 9 clk $end
$var wire 1 : rst_n $end
$var reg 4 B ALU_Ctrl [3:0] $end
$var reg 1 6 A_E $end
$var reg 1 5 A_L $end
$var reg 1 4 B_E $end
$var reg 1 3 B_L $end
$var reg 4 C JMP_Ctrl [3:0] $end
$var reg 4 D MMU_Ctrl [3:0] $end
$var reg 1 - PC_inc $end
$var reg 1 + SP_E $end
$var reg 1 ( S_E $end
$var reg 1 E bus_enable $end
$var reg 1 F halt $end
$var reg 8 G instruction [7:0] $end
$var reg 1 H operand $end
$var reg 8 I operand_buffer [7:0] $end
$var reg 8 J out [7:0] $end
$var reg 2 K status [1:0] $end
$var reg 1 L waiting $end
$var reg 1 M write_waiting $end
$upscope $end
$scope module MMU $end
$var wire 8 N B_Dir [7:0] $end
$var wire 4 O MMU_Ctrl [3:0] $end
$var wire 8 P bus [7:0] $end
$var wire 1 9 clk $end
$var wire 8 Q data_out [7:0] $end
$var wire 1 : rst_n $end
$var wire 1 % rW $end
$var wire 16 R addr_out [15:0] $end
$var wire 8 S SP_Dir [7:0] $end
$var wire 16 T PC [15:0] $end
$var reg 2 U SP_action [1:0] $end
$var reg 16 V addr_external [15:0] $end
$var reg 16 W address [15:0] $end
$var reg 1 X bus_enable $end
$var reg 8 Y data_external [7:0] $end
$var reg 1 Z indexed $end
$var reg 1 [ read $end
$var reg 1 \ stack $end
$var reg 1 ] write $end
$var reg 1 ^ write_L $end
$upscope $end
$scope module PCmover $end
$var wire 4 _ JMP_Ctrl [3:0] $end
$var wire 1 . PC_Dir_L $end
$var wire 8 ` S_Dir_JMP [7:0] $end
$var wire 8 a bus [7:0] $end
$var wire 1 9 clk $end
$var wire 1 : rst_n $end
$var wire 16 b PC_Dir [15:0] $end
$var reg 16 c PC_upd [15:0] $end
$var reg 1 d active $end
$var reg 16 e address [15:0] $end
$upscope $end
$scope module registers $end
$var wire 8 f A_Dir [7:0] $end
$var wire 1 6 A_E $end
$var wire 1 5 A_L $end
$var wire 8 g B_Dir [7:0] $end
$var wire 1 4 B_E $end
$var wire 1 3 B_L $end
$var wire 16 h PC_Dir [15:0] $end
$var wire 1 . PC_Dir_L $end
$var wire 16 i PC_Dir_out [15:0] $end
$var wire 1 - PC_inc $end
$var wire 8 j SP_Dir [7:0] $end
$var wire 1 + SP_E $end
$var wire 1 k SP_L $end
$var wire 2 l SP_action [1:0] $end
$var wire 8 m S_Dir_ALU [7:0] $end
$var wire 8 n S_Dir_JMP [7:0] $end
$var wire 1 ( S_E $end
$var wire 1 ' S_L_ALU $end
$var wire 8 o bus [7:0] $end
$var wire 1 9 clk $end
$var wire 1 : rst_n $end
$var wire 1 p B_Dir_JMP $end
$var reg 8 q A [7:0] $end
$var reg 1 r A_L_ready $end
$var reg 8 s B [7:0] $end
$var reg 1 t B_L_ready $end
$var reg 16 u PC [15:0] $end
$var reg 8 v S [7:0] $end
$var reg 8 w SP [7:0] $end
$var reg 1 x S_L_ready $end
$upscope $end
$upscope $end
$enddefinitions $end
$comment Show the parameter values. $end
$dumpall
$end
#0
$dumpvars
xx
bx w
bx v
bx u
xt
bx s
xr
bx q
xp
bx o
bz n
bz m
bz l
zk
bx j
bx i
bz h
bz g
bx f
bx e
0d
bx c
bz b
bx a
bz `
b0 _
x^
x]
x\
x[
xZ
bx Y
0X
bx W
bx V
bx U
bx T
bx S
bx R
bx Q
bx P
b0 O
bz N
xM
xL
bx K
bx J
bx I
xH
bx G
xF
0E
b0 D
b0 C
b0 B
bx A
bx @
bx ?
b0 >
bx =
bz <
bx ;
0:
09
b0 8
bx 7
06
05
04
03
b0 2
b0 1
bx 0
bz /
0.
x-
bx ,
x+
bx *
bz )
0(
0'
bx &
x%
bx $
bx #
bz "
bz !
$end
#10000
b0 0
b0 T
b0 i
b0 u
19
#20000
09
#30000
bz #
bz ;
bz A
bz P
bz a
bz o
z%
0p
bz &
bz R
0^
b0 ?
b0 @
0x
0t
0r
b11111111 ,
b11111111 S
b11111111 j
b11111111 w
b0 v
b0 s
b0 7
b0 =
b0 f
b0 q
b0 c
b0 W
b0 V
b0 Y
b0 *
b0 U
0\
0Z
0]
0[
b0 J
0+
1-
b0 G
b0 I
0H
0M
0L
0F
b0 K
19
1:
#40000
1L
b110 1
b110 D
b110 O
09
#50000
b1110010 $
b1110010 Q
b0 &
b0 R
b1110010 #
b1110010 ;
b1110010 A
b1110010 P
b1110010 a
b1110010 o
1%
b1 0
b1 T
b1 i
b1 u
1X
1[
19
#60000
b1 K
0L
b1110010 G
0-
b0 1
b0 D
b0 O
09
#70000
bx $
bx Q
bz &
bz R
z%
bz #
bz ;
bz A
bz P
bz a
bz o
0[
0X
19
#80000
1L
1-
b110 1
b110 D
b110 O
09
#90000
b1100 $
b1100 Q
b1 &
b1 R
b1100 #
b1100 ;
b1100 A
b1100 P
b1100 a
b1100 o
1%
b10 0
b10 T
b10 i
b10 u
1X
1[
b1 V
19
#100000
b10 K
0L
b1100 I
0-
b0 1
b0 D
b0 O
09
#110000
bx $
bx Q
bz &
bz R
z%
bz #
bz ;
bz A
bz P
bz a
bz o
0[
0X
19
#120000
b1100 #
b1100 ;
b1100 A
b1100 P
b1100 a
b1100 o
b0 K
1E
b1100 J
15
09
#130000
1r
19
#140000
1L
b110 1
b110 D
b110 O
1-
b1100 7
b1100 =
b1100 f
b1100 q
bz #
bz ;
bz A
bz P
bz a
bz o
05
0E
09
#150000
b11010001 $
b11010001 Q
b10 &
b10 R
b11010001 #
b11010001 ;
b11010001 A
b11010001 P
b11010001 a
b11010001 o
1%
1X
1[
b10 V
b11 0
b11 T
b11 i
b11 u
0r
19
#160000
b10 K
0L
b11010001 G
0-
b0 1
b0 D
b0 O
09
#170000
bx $
bx Q
bz &
bz R
z%
bz #
bz ;
bz A
bz P
bz a
bz o
0[
0X
19
#180000
b1100 #
b1100 ;
b1100 A
b1100 P
b1100 a
b1100 o
b0 K
1M
b1001 1
b1001 D
b1001 O
16
09
#190000
1^
1\
19
#200000
b1100 $
b1100 Q
0%
b111111111 &
b111111111 R
1]
b1100 Y
b111111111 V
0M
bz #
bz ;
bz A
bz P
bz a
bz o
b1 *
b1 U
b111111111 W
06
b0 1
b0 D
b0 O
09
#210000
0\
0^
19
#220000
z%
bz &
bz R
bx $
bx Q
1L
b110 1
b110 D
b110 O
1-
0]
09
#230000
b0 $
b0 Q
b11 &
b11 R
b0 #
b0 ;
b0 A
b0 P
b0 a
b0 o
1%
1X
1[
b11 V
b100 0
b100 T
b100 i
b100 u
19
#240000
b10 K
0L
b0 G
0-
b0 1
b0 D
b0 O
09
#250000
bx $
bx Q
bz &
bz R
z%
bz #
bz ;
bz A
bz P
bz a
bz o
0[
0X
19
#260000
b0 #
b0 ;
b0 A
b0 P
b0 a
b0 o
b0 K
14
1F
09
#270000
19
#280000
bz #
bz ;
bz A
bz P
bz a
bz o
04
09
