TC1_8bit/src/alu.v
module ALU (
        input clk,
        input rst_n,

        inout [7:0] bus,

        input [3:0] ALU_Ctrl,
        input ALU_regselect,

        input [7:0] A_Dir,
        input [7:0] B_Dir
    );

    reg [7:0] sum;
    reg [7:0] out;
    reg active;

    assign bus = (active) ? out : 8'bZ;

    always @(posedge clk) out <= sum;

    always @(negedge clk) begin
        if (rst_n) begin
            if (ALU_Ctrl != 4'b0000) begin
                active = 1; 
                case (ALU_Ctrl)
                    4'b0001 : sum = (A_Dir + bus);
                    4'b0010 : sum = (A_Dir - bus);
                    4'b0011 : sum = (A_Dir & bus);
                    4'b0100 : sum = (A_Dir | bus);
                    4'b0101 : sum = (A_Dir ^ bus); 

                    4'b0110 : sum = (A_Dir << bus);
                    4'b0111 : sum = (A_Dir >> bus);

                    4'b1000 : sum = (8'd1) ? (A_Dir == bus) : 8'd0;
                    4'b1001 : sum = (8'b0) ? (A_Dir == bus) : 8'd1;
                    4'b1010 : sum = (8'b1) ? (A_Dir > bus) : 8'd0;
                    4'b1011 : sum = (8'b1) ? (A_Dir < bus) : 8'd0;
                    4'b1100 : sum = (8'b1) ? (A_Dir >= bus) : 8'd0;
                    4'b1101 : sum = (8'b1) ? (A_Dir <= bus) : 8'd0;
                endcase
            end else active = 0;
        end else active = 0;
    end;

    always @(posedge rst_n) begin
        sum <= 8'd0;
        out <= 8'd0;
        active <= 0;
    end 


endmodule

module PCmover (
        input clk,
        input rst_n,

        input [7:0] bus,
        inout [15:0] PC_Dir,
        input [3:0] JMP_ctrl,
        input [7:0] A_Dir,

        output PC_Dir_L
    );

    reg active;
    reg [15:0] PC_upd;

    assign PC_Dir_L = active;

    assign PC_Dir = (active) ? PC_upd : 16'bZ;

    always @(negedge clk) begin
        if (rst_n) begin
            if (JMP_ctrl != 4'b0000) begin
                active = 1;
                case (JMP_ctrl)
                    4'b0001 : begin
                        PC_upd = bus;
                        active = 1;
                    end
                    4'b0010 : begin
                        if (A_Dir != 7'd0) begin
                            PC_upd = bus;
                            active = 1;
                        end
                    end
                endcase
            end else active = 0;
        end else active = 0;
    end

    always @(posedge rst_n) begin
        active <= 0;
        PC_upd <= 16'd0;
    end

endmodule

TC1_8bit/src/registers.v
module registers (
        input clk,
        input rst_n, 

        inout [7:0] bus,

        input A_E,
        input B_E,
        input PCH_E,
        input PCL_E,
        input A_L,
        input B_L,
        input PCH_L,
        input PCL_L,
        input PC_Dir_L,

        output [7:0] A_Dir,
        output [7:0] B_Dir,
        input [15:0] PC_Dir
    );

    reg [7:0] A;
    reg [7:0] B;

    reg [15:0] PC;

    assign bus = (A_E) ? A : 
                 (B_E) ? B :
                 (PCL_E) ? PC[7:0] :
                 (PCH_E) ? PC[15:8] : 8'bZ;

    assign A_Dir = A;
    assign B_Dir = B; 

    always @(negedge clk) begin
        if (rst_n) begin
            A <= (A_L) ? bus : A;
            B <= (B_L) ? bus : B;
            PC[7:0] <= (PCL_L) ? bus : PC[7:0];
            PC[15:8] <= (PCH_L) ? bus : PC[15:8];
            PC <= (PC_Dir_L) ? PC_Dir : PC;
        end
    end
;
    always @(posedge clk) begin
        if (rst_n) begin
            PC <= PC + 1;
        end else begin
            PC <= 16'd0;
        end
    end

    always @(posedge rst_n) begin
        A <= 8'b0;
        B <= 8'b0;
        PC <= 16'b0;
    end
endmodule

TC1_8bit/src/testbench.v
`timescale 1ns / 1ps

module testbench;

    reg clk;
    reg rst_n;
    wire [7:0] bus;
    wire [7:0] A_Dir;
    wire [7:0] B_Dir;
    wire [15:0] PC_Dir;
    reg bus_sending;

    reg [3:0] ALU_Ctrl;
    reg [3:0] JMP_ctrl;

    assign bus = (bus_sending) ? 8'd12 : 8'bZ;

    reg A_E;
    reg B_E;
    reg A_L;
    reg B_L;
    reg PCH_L;
    reg PCH_E;
    reg PCL_L;
    reg PCL_E;
    
    wire PC_Dir_L;

    ALU ALU (
        .clk(clk),
        .rst_n(rst_n),
        .bus(bus),
        .A_Dir(A_Dir),
        .B_Dir(B_Dir),
        .ALU_Ctrl(ALU_Ctrl)
    );

    registers registers (
        .clk(clk),
        .rst_n(rst_n),
        .bus(bus),
        .A_E(A_E),
        .B_E(B_E),
        .A_L(A_L),
        .B_L(B_L),
        .PCH_E(PCH_E),
        .PCH_L(PCH_L),
        .PCL_E(PCL_E),
        .PCL_L(PCL_L),
        .A_Dir(A_Dir),
        .B_Dir(B_Dir),
        .PC_Dir(PC_Dir),
        .PC_Dir_L(PC_Dir_L)
    );

    PCmover PCmover (
        .clk(clk),
        .rst_n(rst_n),
        .bus(bus),
        .PC_Dir(PC_Dir),
        .PC_Dir_L(PC_Dir_L),
        .JMP_ctrl(JMP_ctrl),
        .A_Dir(A_Dir)
    );

    always begin
        #10 clk = ~clk; 
    end

    initial begin
        clk = 0;
        rst_n = 0;
        bus_sending = 0;
        ALU_Ctrl = 0;

        A_E = 0;
        A_L = 0;
        B_E = 0;
        B_L = 0;
        PCH_L = 0;
        PCH_E = 0;
        PCL_E = 0;
        PCL_L = 0;
        
        $dumpfile("testbench_waveform.vcd");
        $dumpvars(0, testbench);

        #30 rst_n = 1; //reset high
        #10 bus_sending = 1; A_L = 1; //load 12 into A
        #20
        #20 A_L = 0; A_E = 1; JMP_ctrl = 4'b0001;
        #20 A_E = 0; JMP_ctrl = 4'd0;
        #80


        $finish;
    end

endmodule

TC1_8bit/src/testbench_waveform.vcd
$date
	Wed Aug 05 00:19:27 2026
$end
$version
	Icarus Verilog
$end
$timescale
	1ps
$end
$scope module testbench $end
$var wire 8 ! bus [7:0] $end
$var wire 1 " PC_Dir_L $end
$var wire 16 # PC_Dir [15:0] $end
$var wire 8 $ B_Dir [7:0] $end
$var wire 8 % A_Dir [7:0] $end
$var reg 4 & ALU_Ctrl [3:0] $end
$var reg 1 ' A_E $end
$var reg 1 ( A_L $end
$var reg 1 ) B_E $end
$var reg 1 * B_L $end
$var reg 4 + JMP_ctrl [3:0] $end
$var reg 1 , PCH_E $end
$var reg 1 - PCH_L $end
$var reg 1 . PCL_E $end
$var reg 1 / PCL_L $end
$var reg 1 0 bus_sending $end
$var reg 1 1 clk $end
$var reg 1 2 rst_n $end
$scope module ALU $end
$var wire 4 3 ALU_Ctrl [3:0] $end
$var wire 1 4 ALU_regselect $end
$var wire 8 5 bus [7:0] $end
$var wire 1 1 clk $end
$var wire 1 2 rst_n $end
$var wire 8 6 B_Dir [7:0] $end
$var wire 8 7 A_Dir [7:0] $end
$var reg 1 8 active $end
$var reg 8 9 out [7:0] $end
$var reg 8 : sum [7:0] $end
$upscope $end
$scope module PCmover $end
$var wire 4 ; JMP_ctrl [3:0] $end
$var wire 1 " PC_Dir_L $end
$var wire 8 < bus [7:0] $end
$var wire 1 1 clk $end
$var wire 1 2 rst_n $end
$var wire 16 = PC_Dir [15:0] $end
$var wire 8 > A_Dir [7:0] $end
$var reg 16 ? PC_upd [15:0] $end
$var reg 1 @ active $end
$upscope $end
$scope module registers $end
$var wire 8 A A_Dir [7:0] $end
$var wire 1 ' A_E $end
$var wire 1 ( A_L $end
$var wire 8 B B_Dir [7:0] $end
$var wire 1 ) B_E $end
$var wire 1 * B_L $end
$var wire 1 , PCH_E $end
$var wire 1 - PCH_L $end
$var wire 1 . PCL_E $end
$var wire 1 / PCL_L $end
$var wire 16 C PC_Dir [15:0] $end
$var wire 1 " PC_Dir_L $end
$var wire 8 D bus [7:0] $end
$var wire 1 1 clk $end
$var wire 1 2 rst_n $end
$var reg 8 E A [7:0] $end
$var reg 8 F B [7:0] $end
$var reg 16 G PC [15:0] $end
$upscope $end
$upscope $end
$enddefinitions $end
$comment Show the parameter values. $end
$dumpall
$end
#0
$dumpvars
bx G
bx F
bx E
bz D
bz C
bx B
bx A
0@
bx ?
bx >
bz =
bz <
bx ;
bx :
bx 9
08
bx 7
bx 6
bz 5
z4
b0 3
02
01
00
0/
0.
0-
0,
bx +
0*
0)
0(
0'
b0 &
bx %
bx $
bz #
0"
bz !
$end
#10000
b0 G
11
#20000
01
#30000
b1 G
bx 9
b0 :
b0 $
b0 6
b0 B
b0 F
b0 %
b0 7
b0 >
b0 A
b0 E
b0 ?
11
12
#40000
b1100 %
b1100 7
b1100 >
b1100 A
b1100 E
b1100 !
b1100 5
b1100 <
b1100 D
01
1(
10
#50000
b0 9
b10 G
11
#60000
01
#70000
b11 G
11
#80000
bz G
b1100 #
b1100 =
b1100 C
b1100 ?
1"
1@
01
b1 +
b1 ;
1'
0(
#90000
bx G
11
#100000
b1100 G
bz #
bz =
bz C
0"
0@
01
b0 +
b0 ;
0'
#110000
b1101 G
11
#120000
01
#130000
b1110 G
11
#140000
01
#150000
b1111 G
11
#160000
01
#170000
b10000 G
11
